[{"linha":"915","descricao_ponto":"Avenida Nova York próximo ao 54","sequencia":"4","latitude":"-22.8654","longitude":"-43.2537","pontos_turisticos":[]},{"linha":"915","descricao_ponto":"Avenida Vinte De Janeiro próximo ao S/n","sequencia":"1","latitude":"-22.8111","longitude":"-43.2516","pontos_turisticos":[]},{"linha":"915","descricao_ponto":"Avenida Vinte De Janeiro próximo ao 123","sequencia":"5","latitude":"-22.822","longitude":"-43.2324","pontos_turisticos":[]},{"linha":"915","descricao_ponto":"Rua Barreiros próximo ao 250","sequencia":"15","latitude":"-22.8531","longitude":"-43.2531","pontos_turisticos":[]},{"linha":"915","descricao_ponto":"Rua Barreiros próximo ao 451","sequencia":"16","latitude":"-22.8523","longitude":"-43.2546","pontos_turisticos":[]},{"linha":"915","descricao_ponto":"Avenida Postal próximo ao 1","sequencia":"13","latitude":"-22.8516","longitude":"-43.2486","pontos_turisticos":[]},{"linha":"915","descricao_ponto":"Rua Leopoldo Bulhoes próximo ao","sequencia":"2","latitude":"-22.8699","longitude":"-43.2543","pontos_turisticos":[]},{"linha":"915","descricao_ponto":"Avenida Vinte De Janeiro próximo ao S/n","sequencia":"19","latitude":"-22.8111","longitude":"-43.2516","pontos_turisticos":[]},{"linha":"915","descricao_ponto":"Estrada Do Galeao próximo ao S/n","sequencia":"8","latitude":"-22.8324","longitude":"-43.2427","pontos_turisticos":[]},{"linha":"915","descricao_ponto":"Rua Da Regeneracao próximo ao 961","sequencia":"14","latitude":"-22.8543","longitude":"-43.2487","pontos_turisticos":[]},{"linha":"915","descricao_ponto":"Rua Cardoso De Morais próximo ao 535","sequencia":"18","latitude":"-22.8556","longitude":"-43.259","pontos_turisticos":[]},{"linha":"915","descricao_ponto":"Rua Joao Romariz próximo ao 188","sequencia":"17","latitude":"-22.8526","longitude":"-43.2559","pontos_turisticos":[]},{"linha":"915","descricao_ponto":"Avenida Vinte De Janeiro próximo ao 323","sequencia":"3","latitude":"-22.8162","longitude":"-43.241","pontos_turisticos":[]},{"linha":"915","descricao_ponto":"Rua Julio Ribeiro próximo ao 127","sequencia":"5","latitude":"-22.8632","longitude":"-43.2529","pontos_turisticos":[]},{"linha":"915","descricao_ponto":"Avenida Vinte De Janeiro próximo ao 290","sequencia":"18","latitude":"-22.8161","longitude":"-43.2407","pontos_turisticos":[]},{"linha":"915","descricao_ponto":"Estrada Do Galeao próximo ao S/n","sequencia":"7","latitude":"-22.833","longitude":"-43.2391","pontos_turisticos":[]},{"linha":"915","descricao_ponto":"Avenida Dos Campeoes próximo ao 317","sequencia":"11","latitude":"-22.8548","longitude":"-43.2509","pontos_turisticos":[]},{"linha":"915","descricao_ponto":"Avenida Brasil próximo ao 6869","sequencia":"13","latitude":"-22.853","longitude":"-43.2479","pontos_turisticos":[]},{"linha":"915","descricao_ponto":"Avenida Vinte De Janeiro próximo ao 290","sequencia":"17","latitude":"-22.8186","longitude":"-43.237","pontos_turisticos":[]},{"linha":"915","descricao_ponto":"Rua Leopoldo Bulhoes próximo ao 2131","sequencia":"24","latitude":"-22.8686","longitude":"-43.2548","pontos_turisticos":[]},{"linha":"915","descricao_ponto":"Rua Bonsucesso próximo ao 233","sequencia":"6","latitude":"-22.8628","longitude":"-43.2535","pontos_turisticos":[]},{"linha":"915","descricao_ponto":"Avenida Teixeira De Castro próximo ao 122","sequencia":"8","latitude":"-22.8602","longitude":"-43.2538","pontos_turisticos":[]},{"linha":"915","descricao_ponto":"Avenida Teixeira De Castro próximo ao 308","sequencia":"10","latitude":"-22.8564","longitude":"-43.2523","pontos_turisticos":[]},{"linha":"915","descricao_ponto":"Rua Cardoso De Morais próximo ao 193","sequencia":"20","latitude":"-22.8593","longitude":"-43.2563","pontos_turisticos":[]},{"linha":"915","descricao_ponto":"Avenida Postal próximo ao 1","sequencia":"12","latitude":"-22.8534","longitude":"-43.2483","pontos_turisticos":[]},{"linha":"915","descricao_ponto":"Avenida Brigadeiro Trompowski próximo ao S/n","sequencia":"12","latitude":"-22.847","longitude":"-43.2457","pontos_turisticos":[]},{"linha":"915","descricao_ponto":"Avenida Vinte De Janeiro próximo ao 7311","sequencia":"16","latitude":"-22.8333","longitude":"-43.2388","pontos_turisticos":[]},{"linha":"915","descricao_ponto":"Avenida Brigadeiro Trompowski próximo ao S/n","sequencia":"9","latitude":"-22.8444","longitude":"-43.2399","pontos_turisticos":[]},{"linha":"915","descricao_ponto":"Rua Cardoso De Morais próximo ao 82","sequencia":"23","latitude":"-22.8649","longitude":"-43.2548","pontos_turisticos":[]},{"linha":"915","descricao_ponto":"Rua Cardoso De Morais próximo ao 3349","sequencia":"19","latitude":"-22.8568","longitude":"-43.2581","pontos_turisticos":[]},{"linha":"915","descricao_ponto":"Rua Leopoldo Bulhoes próximo ao 2131","sequencia":"1","latitude":"-22.8686","longitude":"-43.2548","pontos_turisticos":[]},{"linha":"915","descricao_ponto":"Avenida Brigadeiro Trompowski próximo ao 222","sequencia":"14","latitude":"-22.8482","longitude":"-43.2451","pontos_turisticos":[]},{"linha":"915","descricao_ponto":"Rua Cardoso De Morais próximo ao 173","sequencia":"21","latitude":"-22.862","longitude":"-43.2545","pontos_turisticos":[]},{"linha":"915","descricao_ponto":"Estrada Do Galeao próximo ao 54","sequencia":"6","latitude":"-22.8254","longitude":"-43.233","pontos_turisticos":[]},{"linha":"915","descricao_ponto":"Avenida Vinte De Janeiro próximo ao 1455","sequencia":"2","latitude":"-22.8146","longitude":"-43.2464","pontos_turisticos":[]},{"linha":"915","descricao_ponto":"Avenida Teixeira De Castro próximo ao 24","sequencia":"7","latitude":"-22.862","longitude":"-43.2539","pontos_turisticos":[]},{"linha":"915","descricao_ponto":"Avenida Vinte De Janeiro próximo ao 1455","sequencia":"20","latitude":"-22.8146","longitude":"-43.2464","pontos_turisticos":[]},{"linha":"915","descricao_ponto":"Avenida Teixeira De Castro próximo ao 245","sequencia":"9","latitude":"-22.8577","longitude":"-43.2525","pontos_turisticos":[]},{"linha":"915","descricao_ponto":"Avenida Vinte De Janeiro próximo ao 323","sequencia":"4","latitude":"-22.8188","longitude":"-43.2371","pontos_turisticos":[]},{"linha":"915","descricao_ponto":"Rua Cardoso De Morais próximo ao 61","sequencia":"22","latitude":"-22.8636","longitude":"-43.2542","pontos_turisticos":[]},{"linha":"915","descricao_ponto":"Rua Leopoldo Bulhoes próximo ao","sequencia":"25","latitude":"-22.8699","longitude":"-43.2543","pontos_turisticos":[]},{"linha":"915","descricao_ponto":"Avenida Brigadeiro Trompowski próximo ao S/n","sequencia":"11","latitude":"-22.8444","longitude":"-43.2399","pontos_turisticos":[]}]