[{"linha":"918","descricao_ponto":"Rua Cairo próximo ao 21","sequencia":"6","latitude":"-22.8885","longitude":"-43.4802","pontos_turisticos":[{"nome":"Parque Municipal Fazenda do Viegas","distancia":606}]},{"linha":"918","descricao_ponto":"Rua Rio Da Prata próximo ao 968","sequencia":"13","latitude":"-22.886","longitude":"-43.4698","pontos_turisticos":[{"nome":"Parque Municipal Fazenda do Viegas","distancia":1562}]},{"linha":"918","descricao_ponto":"Avenida De Santa Cruz próximo ao 1899","sequencia":"26","latitude":"-22.878","longitude":"-43.4408","pontos_turisticos":[]},{"linha":"918","descricao_ponto":"Avenida Dos Democraticos próximo ao 408","sequencia":"122","latitude":"-22.8686","longitude":"-43.2583","pontos_turisticos":[]},{"linha":"918","descricao_ponto":"Avenida Braz De Pina próximo ao 1353","sequencia":"87","latitude":"-22.84","longitude":"-43.3089","pontos_turisticos":[]},{"linha":"918","descricao_ponto":"Rua Uranos próximo ao","sequencia":"107","latitude":"-22.8466","longitude":"-43.2676","pontos_turisticos":[{"nome":"Igreja Nossa Senhora da Penha","distancia":1056},{"nome":"Praia de Ramos","distancia":1970}]},{"linha":"918","descricao_ponto":"Avenida Dos Democraticos próximo ao 1191","sequencia":"117","latitude":"-22.8668","longitude":"-43.2567","pontos_turisticos":[]},{"linha":"918","descricao_ponto":"Avenida Dos Democraticos próximo ao 1806","sequencia":"121","latitude":"-22.8704","longitude":"-43.2584","pontos_turisticos":[]},{"linha":"918","descricao_ponto":"Rua Mucuripe próximo ao 59","sequencia":"1","latitude":"-22.8942","longitude":"-43.4888","pontos_turisticos":[{"nome":"Parque Municipal Fazenda do Viegas","distancia":1056}]},{"linha":"918","descricao_ponto":"Avenida Duque De Caxias próximo ao 1147","sequencia":"38","latitude":"-22.8693","longitude":"-43.4089","pontos_turisticos":[]},{"linha":"918","descricao_ponto":"Rua Carolina Machado próximo ao 667","sequencia":"65","latitude":"-22.8728","longitude":"-43.3435","pontos_turisticos":[]},{"linha":"918","descricao_ponto":"Estrada Padre Roser próximo ao 247","sequencia":"84","latitude":"-22.8413","longitude":"-43.3167","pontos_turisticos":[]},{"linha":"918","descricao_ponto":"Avenida Braz De Pina próximo ao 173","sequencia":"101","latitude":"-22.8424","longitude":"-43.2784","pontos_turisticos":[{"nome":"Igreja Nossa Senhora da Penha","distancia":345}]},{"linha":"918","descricao_ponto":"30585","sequencia":"120","latitude":"-22.8716","longitude":"-43.2588","pontos_turisticos":[]},{"linha":"918","descricao_ponto":"Avenida De Santa Cruz próximo ao 1050","sequencia":"29","latitude":"-22.8779","longitude":"-43.4361","pontos_turisticos":[]},{"linha":"918","descricao_ponto":"Avenida Ministro Edgard Romero próximo ao 60","sequencia":"72","latitude":"-22.8662","longitude":"-43.3345","pontos_turisticos":[]},{"linha":"918","descricao_ponto":"Avenida Braz De Pina próximo ao 1153","sequencia":"90","latitude":"-22.8406","longitude":"-43.3023","pontos_turisticos":[]},{"linha":"918","descricao_ponto":"Rua Uranos próximo ao 1001","sequencia":"111","latitude":"-22.8532","longitude":"-43.2624","pontos_turisticos":[{"nome":"Igreja Nossa Senhora da Penha","distancia":1801}]},{"linha":"918","descricao_ponto":"Rua Francisco Real próximo ao 57","sequencia":"24","latitude":"-22.8771","longitude":"-43.4461","pontos_turisticos":[]},{"linha":"918","descricao_ponto":"Rua Uranos próximo ao","sequencia":"106","latitude":"-22.8445","longitude":"-43.2686","pontos_turisticos":[{"nome":"Igreja Nossa Senhora da Penha","distancia":952},{"nome":"Praia de Ramos","distancia":1974}]},{"linha":"918","descricao_ponto":"Rua Adalgiza Aleixo próximo ao 85","sequencia":"55","latitude":"-22.8659","longitude":"-43.3587","pontos_turisticos":[{"nome":"Teatro Armando Gonzaga","distancia":1484}]},{"linha":"918","descricao_ponto":"Rua Joao Vicente próximo ao 1125","sequencia":"57","latitude":"-22.8646","longitude":"-43.3618","pontos_turisticos":[{"nome":"Teatro Armando Gonzaga","distancia":1175}]},{"linha":"918","descricao_ponto":"Avenida Ministro Edgard Romero próximo ao 782","sequencia":"74","latitude":"-22.8609","longitude":"-43.3299","pontos_turisticos":[]},{"linha":"918","descricao_ponto":"Avenida Monsenhor Felix próximo ao 572","sequencia":"79","latitude":"-22.8481","longitude":"-43.3251","pontos_turisticos":[]},{"linha":"918","descricao_ponto":"Rua Rio Da Prata próximo ao 1635","sequencia":"9","latitude":"-22.8862","longitude":"-43.4782","pontos_turisticos":[{"nome":"Parque Municipal Fazenda do Viegas","distancia":706}]},{"linha":"918","descricao_ponto":"Avenida Ministro Edgard Romero próximo ao 871","sequencia":"75","latitude":"-22.8586","longitude":"-43.3294","pontos_turisticos":[]},{"linha":"918","descricao_ponto":"Avenida Monsenhor Felix próximo ao 196","sequencia":"77","latitude":"-22.8525","longitude":"-43.3283","pontos_turisticos":[]},{"linha":"918","descricao_ponto":"Rua Uranos próximo ao 2019","sequencia":"116","latitude":"-22.8657","longitude":"-43.2561","pontos_turisticos":[]},{"linha":"918","descricao_ponto":"Avenida Duque De Caxias próximo ao 2001","sequencia":"44","latitude":"-22.8605","longitude":"-43.3908","pontos_turisticos":[{"nome":"Teatro Armando Gonzaga","distancia":1900}]},{"linha":"918","descricao_ponto":"Rua Carolina Machado próximo ao 1218","sequencia":"61","latitude":"-22.8667","longitude":"-43.3539","pontos_turisticos":[{"nome":"Teatro Armando Gonzaga","distancia":1978}]},{"linha":"918","descricao_ponto":"Avenida Monsenhor Felix próximo ao 1131","sequencia":"80","latitude":"-22.8455","longitude":"-43.324","pontos_turisticos":[]},{"linha":"918","descricao_ponto":"Rua Uranos próximo ao 1207","sequencia":"110","latitude":"-22.8518","longitude":"-43.2639","pontos_turisticos":[{"nome":"Igreja Nossa Senhora da Penha","distancia":1593}]},{"linha":"918","descricao_ponto":"Avenida De Santa Cruz próximo ao 1401","sequencia":"25","latitude":"-22.8779","longitude":"-43.4419","pontos_turisticos":[]},{"linha":"918","descricao_ponto":"Avenida De Santa Cruz próximo ao 241","sequencia":"32","latitude":"-22.8788","longitude":"-43.4265","pontos_turisticos":[]},{"linha":"918","descricao_ponto":"Estrada General Canrobert Da Costa próximo ao 41","sequencia":"36","latitude":"-22.8718","longitude":"-43.4155","pontos_turisticos":[]},{"linha":"918","descricao_ponto":"Rua Cairo próximo ao 282","sequencia":"7","latitude":"-22.8874","longitude":"-43.4805","pontos_turisticos":[{"nome":"Parque Municipal Fazenda do Viegas","distancia":517}]},{"linha":"918","descricao_ponto":"Rua Francisco Real próximo ao 1125","sequencia":"19","latitude":"-22.8795","longitude":"-43.4588","pontos_turisticos":[]},{"linha":"918","descricao_ponto":"Avenida Ministro Edgard Romero próximo ao 612","sequencia":"73","latitude":"-22.8636","longitude":"-43.3329","pontos_turisticos":[]},{"linha":"918","descricao_ponto":"Rua Dos Acudes próximo ao 495","sequencia":"15","latitude":"-22.8804","longitude":"-43.4688","pontos_turisticos":[{"nome":"Parque Municipal Fazenda do Viegas","distancia":1752}]},{"linha":"918","descricao_ponto":"Avenida Duque De Caxias próximo ao 2678","sequencia":"39","latitude":"-22.8679","longitude":"-43.4062","pontos_turisticos":[]},{"linha":"918","descricao_ponto":"Rua Joao Vicente próximo ao 816","sequencia":"51","latitude":"-22.8634","longitude":"-43.3663","pontos_turisticos":[{"nome":"Teatro Armando Gonzaga","distancia":756}]},{"linha":"918","descricao_ponto":"Rua Joao Vicente próximo ao 1121","sequencia":"56","latitude":"-22.8648","longitude":"-43.3605","pontos_turisticos":[{"nome":"Teatro Armando Gonzaga","distancia":1305}]},{"linha":"918","descricao_ponto":"Avenida Ministro Edgard Romero próximo ao 338","sequencia":"71","latitude":"-22.8694","longitude":"-43.3353","pontos_turisticos":[]},{"linha":"918","descricao_ponto":"Avenida Braz De Pina próximo ao 2255","sequencia":"96","latitude":"-22.8379","longitude":"-43.2862","pontos_turisticos":[{"nome":"Igreja Nossa Senhora da Penha","distancia":1201}]},{"linha":"918","descricao_ponto":"Rua Concordia próximo ao 2940","sequencia":"37","latitude":"-22.8703","longitude":"-43.4117","pontos_turisticos":[]},{"linha":"918","descricao_ponto":"Avenida Duque De Caxias próximo ao 1410","sequencia":"42","latitude":"-22.8636","longitude":"-43.3973","pontos_turisticos":[]},{"linha":"918","descricao_ponto":"Avenida Sao Sebastiao próximo ao 1807","sequencia":"46","latitude":"-22.859","longitude":"-43.3817","pontos_turisticos":[{"nome":"Teatro Armando Gonzaga","distancia":1158}]},{"linha":"918","descricao_ponto":"Estrada General Canrobert Da Costa próximo ao 1114","sequencia":"35","latitude":"-22.8731","longitude":"-43.4171","pontos_turisticos":[]},{"linha":"918","descricao_ponto":"Rua Carolina Machado próximo ao 359","sequencia":"68","latitude":"-22.877","longitude":"-43.3363","pontos_turisticos":[]},{"linha":"918","descricao_ponto":"Avenida Itaoca próximo ao","sequencia":"123","latitude":"-22.8676","longitude":"-43.2568","pontos_turisticos":[]},{"linha":"918","descricao_ponto":"Rua Rio Da Prata próximo ao 136","sequencia":"8","latitude":"-22.8863","longitude":"-43.48","pontos_turisticos":[{"nome":"Parque Municipal Fazenda do Viegas","distancia":526}]},{"linha":"918","descricao_ponto":"Avenida De Santa Cruz próximo ao 1313","sequencia":"28","latitude":"-22.8781","longitude":"-43.4376","pontos_turisticos":[]},{"linha":"918","descricao_ponto":"Estrada General Canrobert Da Costa próximo ao 566","sequencia":"33","latitude":"-22.8779","longitude":"-43.423","pontos_turisticos":[]},{"linha":"918","descricao_ponto":"Rua Joao Vicente próximo ao 516","sequencia":"49","latitude":"-22.8615","longitude":"-43.3704","pontos_turisticos":[{"nome":"Teatro Armando Gonzaga","distancia":561}]},{"linha":"918","descricao_ponto":"Avenida Braz De Pina próximo ao 247","sequencia":"98","latitude":"-22.8401","longitude":"-43.2817","pontos_turisticos":[{"nome":"Igreja Nossa Senhora da Penha","distancia":716}]},{"linha":"918","descricao_ponto":"Rua Rio Da Prata próximo ao 1531","sequencia":"12","latitude":"-22.886","longitude":"-43.4716","pontos_turisticos":[{"nome":"Parque Municipal Fazenda do Viegas","distancia":1378}]},{"linha":"918","descricao_ponto":"Rua Carolina Machado próximo ao 1136","sequencia":"62","latitude":"-22.8675","longitude":"-43.3526","pontos_turisticos":[]},{"linha":"918","descricao_ponto":"Rua Carolina Machado próximo ao 894","sequencia":"64","latitude":"-22.8707","longitude":"-43.3471","pontos_turisticos":[]},{"linha":"918","descricao_ponto":"Rua Ibiapina próximo ao 105","sequencia":"105","latitude":"-22.8426","longitude":"-43.2716","pontos_turisticos":[{"nome":"Igreja Nossa Senhora da Penha","distancia":714}]},{"linha":"918","descricao_ponto":"Rua Marmiari próximo ao 160","sequencia":"4","latitude":"-22.8907","longitude":"-43.4821","pontos_turisticos":[{"nome":"Parque Municipal Fazenda do Viegas","distancia":666}]},{"linha":"918","descricao_ponto":"Rua Uranos próximo ao 1429","sequencia":"108","latitude":"-22.8477","longitude":"-43.2672","pontos_turisticos":[{"nome":"Igreja Nossa Senhora da Penha","distancia":1118},{"nome":"Praia de Ramos","distancia":1992}]},{"linha":"918","descricao_ponto":"Rua Uranos próximo ao 773","sequencia":"113","latitude":"-22.8563","longitude":"-43.2593","pontos_turisticos":[]},{"linha":"918","descricao_ponto":"Rua Francisco Real próximo ao 655","sequencia":"21","latitude":"-22.8795","longitude":"-43.4545","pontos_turisticos":[]},{"linha":"918","descricao_ponto":"Avenida Braz De Pina próximo ao 131","sequencia":"100","latitude":"-22.8417","longitude":"-43.2791","pontos_turisticos":[{"nome":"Igreja Nossa Senhora da Penha","distancia":438}]},{"linha":"918","descricao_ponto":"Rua Uranos próximo ao 513","sequencia":"115","latitude":"-22.862","longitude":"-43.2573","pontos_turisticos":[]},{"linha":"918","descricao_ponto":"Avenida Monsenhor Felix próximo ao 60","sequencia":"76","latitude":"-22.8553","longitude":"-43.3293","pontos_turisticos":[]},{"linha":"918","descricao_ponto":"Rua Rio Da Prata próximo ao 1692","sequencia":"10","latitude":"-22.8862","longitude":"-43.4766","pontos_turisticos":[{"nome":"Parque Municipal Fazenda do Viegas","distancia":869}]},{"linha":"918","descricao_ponto":"Rua Francisco Real próximo ao 1353","sequencia":"18","latitude":"-22.8796","longitude":"-43.4632","pontos_turisticos":[]},{"linha":"918","descricao_ponto":"Avenida Duque De Caxias próximo ao 2229","sequencia":"40","latitude":"-22.8664","longitude":"-43.4031","pontos_turisticos":[]},{"linha":"918","descricao_ponto":"Estrada Padre Roser próximo ao 753","sequencia":"82","latitude":"-22.8424","longitude":"-43.321","pontos_turisticos":[]},{"linha":"918","descricao_ponto":"Avenida Dos Democraticos próximo ao 1791","sequencia":"118","latitude":"-22.8681","longitude":"-43.258","pontos_turisticos":[]},{"linha":"918","descricao_ponto":"Rua Paulo Rola próximo ao 248","sequencia":"5","latitude":"-22.8897","longitude":"-43.4808","pontos_turisticos":[{"nome":"Parque Municipal Fazenda do Viegas","distancia":649}]},{"linha":"918","descricao_ponto":"Rua Divisoria próximo ao 1","sequencia":"53","latitude":"-22.8651","longitude":"-43.3628","pontos_turisticos":[{"nome":"Teatro Armando Gonzaga","distancia":1067}]},{"linha":"918","descricao_ponto":"Rua Carolina Machado próximo ao 1330","sequencia":"60","latitude":"-22.8654","longitude":"-43.3562","pontos_turisticos":[{"nome":"Teatro Armando Gonzaga","distancia":1741}]},{"linha":"918","descricao_ponto":"Rua Francisco Real próximo ao 975","sequencia":"20","latitude":"-22.8795","longitude":"-43.4565","pontos_turisticos":[]},{"linha":"918","descricao_ponto":"Rua Carolina Machado próximo ao 519","sequencia":"66","latitude":"-22.8743","longitude":"-43.3411","pontos_turisticos":[]},{"linha":"918","descricao_ponto":"Rua Carolina Machado próximo ao 504","sequencia":"67","latitude":"-22.8753","longitude":"-43.3394","pontos_turisticos":[]},{"linha":"918","descricao_ponto":"Avenida Braz De Pina próximo ao 1195","sequencia":"88","latitude":"-22.8404","longitude":"-43.3071","pontos_turisticos":[]},{"linha":"918","descricao_ponto":"Avenida Braz De Pina próximo ao 811","sequencia":"95","latitude":"-22.8377","longitude":"-43.2892","pontos_turisticos":[{"nome":"Igreja Nossa Senhora da Penha","distancia":1449}]},{"linha":"918","descricao_ponto":"Rua Joao Vicente próximo ao 50","sequencia":"48","latitude":"-22.8589","longitude":"-43.3759","pontos_turisticos":[{"nome":"Teatro Armando Gonzaga","distancia":821}]},{"linha":"918","descricao_ponto":"Avenida Dos Democraticos próximo ao 1157","sequencia":"119","latitude":"-22.87","longitude":"-43.2585","pontos_turisticos":[]},{"linha":"918","descricao_ponto":"Rua Francisco Real próximo ao 215","sequencia":"22","latitude":"-22.8794","longitude":"-43.452","pontos_turisticos":[]},{"linha":"918","descricao_ponto":"Rua Carolina Machado próximo ao 979","sequencia":"63","latitude":"-22.8693","longitude":"-43.3494","pontos_turisticos":[]},{"linha":"918","descricao_ponto":"Avenida Braz De Pina próximo ao 1421","sequencia":"86","latitude":"-22.8398","longitude":"-43.3104","pontos_turisticos":[]},{"linha":"918","descricao_ponto":"Avenida Braz De Pina próximo ao 785","sequencia":"92","latitude":"-22.8395","longitude":"-43.2971","pontos_turisticos":[]},{"linha":"918","descricao_ponto":"Avenida Nossa Senhora Da Penha próximo ao 121","sequencia":"102","latitude":"-22.8422","longitude":"-43.2775","pontos_turisticos":[{"nome":"Igreja Nossa Senhora da Penha","distancia":364}]},{"linha":"918","descricao_ponto":"Avenida De Santa Cruz próximo ao 1697","sequencia":"27","latitude":"-22.878","longitude":"-43.4394","pontos_turisticos":[]},{"linha":"918","descricao_ponto":"Avenida De Santa Cruz próximo ao 566","sequencia":"31","latitude":"-22.8785","longitude":"-43.4292","pontos_turisticos":[]},{"linha":"918","descricao_ponto":"Rua Oscar Schade próximo ao 802","sequencia":"2","latitude":"-22.8954","longitude":"-43.4864","pontos_turisticos":[{"nome":"Parque Municipal Fazenda do Viegas","distancia":1125}]},{"linha":"918","descricao_ponto":"Avenida De Santa Cruz próximo ao 1098","sequencia":"30","latitude":"-22.878","longitude":"-43.4341","pontos_turisticos":[]},{"linha":"918","descricao_ponto":"Rua Carolina Machado próximo ao 1456","sequencia":"59","latitude":"-22.8644","longitude":"-43.3592","pontos_turisticos":[{"nome":"Teatro Armando Gonzaga","distancia":1442}]},{"linha":"918","descricao_ponto":"Avenida Sao Sebastiao próximo ao 1649","sequencia":"45","latitude":"-22.8593","longitude":"-43.3848","pontos_turisticos":[{"nome":"Teatro Armando Gonzaga","distancia":1395}]},{"linha":"918","descricao_ponto":"Rua Joao Vicente próximo ao 48","sequencia":"52","latitude":"-22.8644","longitude":"-43.3637","pontos_turisticos":[{"nome":"Teatro Armando Gonzaga","distancia":985}]},{"linha":"918","descricao_ponto":"Rua Carolina Machado próximo ao 1603","sequencia":"58","latitude":"-22.864","longitude":"-43.3621","pontos_turisticos":[{"nome":"Teatro Armando Gonzaga","distancia":1154}]},{"linha":"918","descricao_ponto":"Avenida Monsenhor Felix próximo ao 340","sequencia":"78","latitude":"-22.8504","longitude":"-43.326","pontos_turisticos":[]},{"linha":"918","descricao_ponto":"Estrada General Canrobert Da Costa próximo ao 1114","sequencia":"34","latitude":"-22.8752","longitude":"-43.4196","pontos_turisticos":[]},{"linha":"918","descricao_ponto":"Avenida Duque De Caxias próximo ao 760","sequencia":"43","latitude":"-22.8626","longitude":"-43.3952","pontos_turisticos":[]},{"linha":"918","descricao_ponto":"Estrada Padre Roser próximo ao 1131","sequencia":"81","latitude":"-22.8437","longitude":"-43.3227","pontos_turisticos":[]},{"linha":"918","descricao_ponto":"Avenida Braz De Pina próximo ao 1047","sequencia":"89","latitude":"-22.8408","longitude":"-43.3035","pontos_turisticos":[]},{"linha":"918","descricao_ponto":"Avenida Braz De Pina próximo ao 703","sequencia":"94","latitude":"-22.8378","longitude":"-43.2912","pontos_turisticos":[{"nome":"Igreja Nossa Senhora da Penha","distancia":1613}]},{"linha":"918","descricao_ponto":"Avenida Braz De Pina próximo ao 4392","sequencia":"99","latitude":"-22.8408","longitude":"-43.2807","pontos_turisticos":[{"nome":"Igreja Nossa Senhora da Penha","distancia":595}]},{"linha":"918","descricao_ponto":"Rua Monsenhor Alves Rocha próximo ao 181","sequencia":"103","latitude":"-22.842","longitude":"-43.2764","pontos_turisticos":[{"nome":"Igreja Nossa Senhora da Penha","distancia":412}]},{"linha":"918","descricao_ponto":"Rua Da Feira próximo ao 1969","sequencia":"16","latitude":"-22.8801","longitude":"-43.4674","pontos_turisticos":[{"nome":"Parque Municipal Fazenda do Viegas","distancia":1898}]},{"linha":"918","descricao_ponto":"Praca Abrolhos V Teresinha próximo ao 25","sequencia":"23","latitude":"-22.8781","longitude":"-43.4478","pontos_turisticos":[]},{"linha":"918","descricao_ponto":"Rua Joao Vicente próximo ao 1175","sequencia":"47","latitude":"-22.8585","longitude":"-43.3785","pontos_turisticos":[{"nome":"Teatro Armando Gonzaga","distancia":982}]},{"linha":"918","descricao_ponto":"Rua Joao Vicente próximo ao 1493","sequencia":"50","latitude":"-22.8621","longitude":"-43.3691","pontos_turisticos":[{"nome":"Teatro Armando Gonzaga","distancia":590}]},{"linha":"918","descricao_ponto":"Estrada Padre Roser próximo ao 1485","sequencia":"85","latitude":"-22.8409","longitude":"-43.3154","pontos_turisticos":[]},{"linha":"918","descricao_ponto":"Avenida Braz De Pina próximo ao 929","sequencia":"91","latitude":"-22.8401","longitude":"-43.2999","pontos_turisticos":[]},{"linha":"918","descricao_ponto":"Avenida Duque De Caxias próximo ao 1691","sequencia":"41","latitude":"-22.8645","longitude":"-43.3991","pontos_turisticos":[]},{"linha":"918","descricao_ponto":"Rua Francisco Real próximo ao 1869","sequencia":"17","latitude":"-22.8796","longitude":"-43.4647","pontos_turisticos":[]},{"linha":"918","descricao_ponto":"Avenida Braz De Pina próximo ao 611","sequencia":"93","latitude":"-22.8382","longitude":"-43.2933","pontos_turisticos":[{"nome":"Igreja Nossa Senhora da Penha","distancia":1778}]},{"linha":"918","descricao_ponto":"Rua Uranos próximo ao 1335","sequencia":"109","latitude":"-22.8501","longitude":"-43.2653","pontos_turisticos":[{"nome":"Igreja Nossa Senhora da Penha","distancia":1384},{"nome":"Praia de Ramos","distancia":1984}]},{"linha":"918","descricao_ponto":"Rua Dos Acudes próximo ao 790","sequencia":"14","latitude":"-22.883","longitude":"-43.4688","pontos_turisticos":[{"nome":"Parque Municipal Fazenda do Viegas","distancia":1683}]},{"linha":"918","descricao_ponto":"Rua Uranos próximo ao 919","sequencia":"112","latitude":"-22.8552","longitude":"-43.2601","pontos_turisticos":[]},{"linha":"918","descricao_ponto":"Rua Rio Da Prata próximo ao 1464","sequencia":"11","latitude":"-22.8861","longitude":"-43.4755","pontos_turisticos":[{"nome":"Parque Municipal Fazenda do Viegas","distancia":980}]},{"linha":"918","descricao_ponto":"Estrada Padre Roser próximo ao 213","sequencia":"83","latitude":"-22.8416","longitude":"-43.3185","pontos_turisticos":[]},{"linha":"918","descricao_ponto":"Rua Ibiapina próximo ao 179","sequencia":"104","latitude":"-22.8421","longitude":"-43.2733","pontos_turisticos":[{"nome":"Igreja Nossa Senhora da Penha","distancia":596}]},{"linha":"918","descricao_ponto":"Rua Uranos próximo ao","sequencia":"114","latitude":"-22.8598","longitude":"-43.2581","pontos_turisticos":[]},{"linha":"918","descricao_ponto":"Rua Francisco Teotonio próximo ao 473","sequencia":"3","latitude":"-22.8939","longitude":"-43.4846","pontos_turisticos":[{"nome":"Parque Municipal Fazenda do Viegas","distancia":951}]},{"linha":"918","descricao_ponto":"Rua Gita próximo ao 197","sequencia":"54","latitude":"-22.8668","longitude":"-43.3627","pontos_turisticos":[{"nome":"Teatro Armando Gonzaga","distancia":1079}]},{"linha":"918","descricao_ponto":"Rua Consel Galvao próximo ao 176","sequencia":"69","latitude":"-22.8734","longitude":"-43.3357","pontos_turisticos":[]},{"linha":"918","descricao_ponto":"Avenida Ministro Edgard Romero próximo ao 239","sequencia":"70","latitude":"-22.8707","longitude":"-43.3357","pontos_turisticos":[]},{"linha":"918","descricao_ponto":"Avenida Braz De Pina próximo ao 363","sequencia":"97","latitude":"-22.8388","longitude":"-43.2838","pontos_turisticos":[{"nome":"Igreja Nossa Senhora da Penha","distancia":960}]}]